{
    "eClass": "http://www.eclipse.org/emf/2002/Ecore#//EClass",
    "eSuperTypes": [
        {
            "eClass": "http://www.eclipse.org/emf/2002/Ecore#//EClass",
            "$ref": "#//IfcRepresentationContext"
        }
    ],
    "name": "IfcGeometricRepresentationContext",
    "eStructuralFeatures": [
        {
            "eClass": "http://www.eclipse.org/emf/2002/Ecore#//EAttribute",
            "eType": {
                "eClass": "http://www.eclipse.org/emf/2002/Ecore#//EClass",
                "$ref": "#//IfcDimensionCount"
            },
            "lowerBound": 1,
            "name": "CoordinateSpaceDimension",
            "required": true
        },
        {
            "eClass": "http://www.eclipse.org/emf/2002/Ecore#//EAttribute",
            "eType": {
                "eClass": "http://www.eclipse.org/emf/2002/Ecore#//EClass",
                "$ref": "#//IfcReal"
            },
            "name": "Precision"
        },
        {
            "eClass": "http://www.eclipse.org/emf/2002/Ecore#//EAttribute",
            "eType": {
                "eClass": "http://www.eclipse.org/emf/2002/Ecore#//EClass",
                "$ref": "#//IfcAxis2Placement"
            },
            "lowerBound": 1,
            "name": "WorldCoordinateSystem",
            "required": true
        }
    ]
}